{"chunk_definitions":[{"chunk_id":"csetup_chunk","chunk_label":"setup","document_id":"BC8B38BD","expansion_state":0,"options":{"engine":"r","include":false,"label":"setup"},"row":9,"row_count":1,"visible":true},{"chunk_id":"cyhham8x1ki73","chunk_label":"unnamed-chunk-1","document_id":"BC8B38BD","expansion_state":0,"options":{"engine":"r","label":"unnamed-chunk-1","message":false},"row":17,"row_count":1,"visible":true},{"chunk_id":"cb5mg0jvbj1s9","chunk_label":"unnamed-chunk-2","document_id":"BC8B38BD","expansion_state":0,"options":{"engine":"r","label":"unnamed-chunk-2","message":false},"row":35,"row_count":1,"visible":true},{"chunk_id":"c32a2bi9zeor7","chunk_label":"unnamed-chunk-3","document_id":"BC8B38BD","expansion_state":0,"options":{"engine":"r","include":false,"label":"unnamed-chunk-3","message":false},"row":55,"row_count":1,"visible":true},{"chunk_id":"cm0i04eo9ds6s","chunk_label":"unnamed-chunk-4","document_id":"BC8B38BD","expansion_state":0,"options":{"engine":"r","label":"unnamed-chunk-4","message":false},"row":61,"row_count":1,"visible":true},{"chunk_id":"cgxtet9nkmrml","chunk_label":"unnamed-chunk-6","document_id":"BC8B38BD","expansion_state":0,"options":{"echo":false,"engine":"r","label":"unnamed-chunk-5"},"row":77,"row_count":1,"visible":true},{"chunk_id":"ck1x0pzrp638y","chunk_label":"unnamed-chunk-7","document_id":"BC8B38BD","expansion_state":0,"options":{"engine":"r","fig.height":7.500000000000001,"fig.width":10,"label":"unnamed-chunk-6"},"row":110,"row_count":1,"visible":true},{"chunk_id":"c1z3c4a5uhdhq","chunk_label":"unnamed-chunk-8","document_id":"BC8B38BD","expansion_state":0,"options":{"echo":false,"engine":"r","fig.height":7.500000000000001,"fig.width":10,"label":"unnamed-chunk-7"},"row":121,"row_count":1,"visible":true},{"chunk_id":"c6x8ilan19wec","chunk_label":"unnamed-chunk-9","document_id":"BC8B38BD","expansion_state":0,"options":{"echo":false,"engine":"r","label":"unnamed-chunk-8"},"row":128,"row_count":1,"visible":true},{"chunk_id":"c337h5v9m53ue","chunk_label":"unnamed-chunk-10","document_id":"BC8B38BD","expansion_state":0,"options":{"echo":false,"engine":"r","label":"unnamed-chunk-17"},"row":136,"row_count":1,"visible":true},{"chunk_id":"cmneoweyi7uo9","chunk_label":"unnamed-chunk-11","document_id":"BC8B38BD","expansion_state":0,"options":{"echo":false,"engine":"r","fig.height":3.500000000000001,"fig.width":5,"label":"unnamed-chunk-19"},"row":167,"row_count":1,"visible":true}],"chunk_rendered_width":400,"default_chunk_options":{"echo":true,"error":false,"fig.height":7.500000000000004,"fig.width":10.00000000000000},"doc_write_time":1581869419,"working_dir":null}